{
  "Core Color Token/Default": {
    "color": {
      "asparagus-50": {
        "$type": "color",
        "$value": "#f0f5ef"
      },
      "asparagus-100": {
        "$type": "color",
        "$value": "#d1e0cd"
      },
      "asparagus-200": {
        "$type": "color",
        "$value": "#bad1b5"
      },
      "asparagus-300": {
        "$type": "color",
        "$value": "#9bbd93"
      },
      "asparagus-400": {
        "$type": "color",
        "$value": "#88b07e"
      },
      "asparagus-500": {
        "$type": "color",
        "$value": "#6a9c5e"
      },
      "asparagus-600": {
        "$type": "color",
        "$value": "#608e56"
      },
      "asparagus-700": {
        "$type": "color",
        "$value": "#4b6f43"
      },
      "asparagus-800": {
        "$type": "color",
        "$value": "#3a5634"
      },
      "asparagus-900": {
        "$type": "color",
        "$value": "#2d4227"
      },
      "red-50": {
        "$type": "color",
        "$value": "#fbe6e6"
      },
      "red-100": {
        "$type": "color",
        "$value": "#f3b0b0"
      },
      "red-200": {
        "$type": "color",
        "$value": "#ee8a8a"
      },
      "red-300": {
        "$type": "color",
        "$value": "#e65454"
      },
      "red-400": {
        "$type": "color",
        "$value": "#e13333"
      },
      "red-500": {
        "$type": "color",
        "$value": "#d90000"
      },
      "red-600": {
        "$type": "color",
        "$value": "#c50000"
      },
      "red-700": {
        "$type": "color",
        "$value": "#9a0000"
      },
      "red-800": {
        "$type": "color",
        "$value": "#770000"
      },
      "red-900": {
        "$type": "color",
        "$value": "#5b0000"
      },
      "orange-50": {
        "$type": "color",
        "$value": "#fbebe7"
      },
      "orange-100": {
        "$type": "color",
        "$value": "#f4c0b3"
      },
      "orange-200": {
        "$type": "color",
        "$value": "#eea28f"
      },
      "orange-300": {
        "$type": "color",
        "$value": "#e6785c"
      },
      "orange-400": {
        "$type": "color",
        "$value": "#e15d3c"
      },
      "orange-500": {
        "$type": "color",
        "$value": "#da350b"
      },
      "orange-600": {
        "$type": "color",
        "$value": "#c6300a"
      },
      "orange-700": {
        "$type": "color",
        "$value": "#9b2608"
      },
      "orange-800": {
        "$type": "color",
        "$value": "#781d06"
      },
      "orange-900": {
        "$type": "color",
        "$value": "#5c1605"
      },
      "green-50": {
        "$type": "color",
        "$value": "#e6f3e6"
      },
      "green-100": {
        "$type": "color",
        "$value": "#b3d9b0"
      },
      "green-200": {
        "$type": "color",
        "$value": "#8ec68a"
      },
      "green-300": {
        "$type": "color",
        "$value": "#5aad55"
      },
      "green-400": {
        "$type": "color",
        "$value": "#3a9d34"
      },
      "green-500": {
        "$type": "color",
        "$value": "#098401"
      },
      "green-600": {
        "$type": "color",
        "$value": "#087801"
      },
      "green-700": {
        "$type": "color",
        "$value": "#065e01"
      },
      "green-800": {
        "$type": "color",
        "$value": "#054901"
      },
      "green-900": {
        "$type": "color",
        "$value": "#043700"
      },
      "blue-50": {
        "$type": "color",
        "$value": "#e6eefb"
      },
      "blue-100": {
        "$type": "color",
        "$value": "#b2cbf2"
      },
      "blue-200": {
        "$type": "color",
        "$value": "#8db1eb"
      },
      "blue-300": {
        "$type": "color",
        "$value": "#5a8ee2"
      },
      "blue-400": {
        "$type": "color",
        "$value": "#3978dd"
      },
      "blue-500": {
        "$type": "color",
        "$value": "#0856d4"
      },
      "blue-600": {
        "$type": "color",
        "$value": "#074ec1"
      },
      "blue-700": {
        "$type": "color",
        "$value": "#063d97"
      },
      "blue-800": {
        "$type": "color",
        "$value": "#042f75"
      },
      "blue-900": {
        "$type": "color",
        "$value": "#032459"
      },
      "dandelion-50": {
        "$type": "color",
        "$value": "#fffbef"
      },
      "dandelion-100": {
        "$type": "color",
        "$value": "#fef2cc"
      },
      "dandelion-200": {
        "$type": "color",
        "$value": "#feecb4"
      },
      "dandelion-300": {
        "$type": "color",
        "$value": "#fde392"
      },
      "dandelion-400": {
        "$type": "color",
        "$value": "#fddd7d"
      },
      "dandelion-500": {
        "$type": "color",
        "$value": "#fcd55c"
      },
      "dandelion-600": {
        "$type": "color",
        "$value": "#e5c254"
      },
      "dandelion-700": {
        "$type": "color",
        "$value": "#b39741"
      },
      "dandelion-800": {
        "$type": "color",
        "$value": "#8b7533"
      },
      "dandelion-900": {
        "$type": "color",
        "$value": "#6a5927"
      },
      "froly-50": {
        "$type": "color",
        "$value": "#fcf1f1"
      },
      "froly-100": {
        "$type": "color",
        "$value": "#f7d4d4"
      },
      "froly-200": {
        "$type": "color",
        "$value": "#f3bfbf"
      },
      "froly-300": {
        "$type": "color",
        "$value": "#eea1a1"
      },
      "froly-400": {
        "$type": "color",
        "$value": "#ea8f8f"
      },
      "froly-500": {
        "$type": "color",
        "$value": "#e57373"
      },
      "froly-600": {
        "$type": "color",
        "$value": "#d06969"
      },
      "froly-700": {
        "$type": "color",
        "$value": "#a35252"
      },
      "froly-800": {
        "$type": "color",
        "$value": "#7e3f3f"
      },
      "froly-900": {
        "$type": "color",
        "$value": "#603030"
      },
      "Neutral-0": {
        "$type": "color",
        "$value": "#ffffff"
      },
      "Neutral-50": {
        "$type": "color",
        "$value": "#f3f4f6"
      },
      "Neutral-100": {
        "$type": "color",
        "$value": "#d9dde2"
      },
      "Neutral-200": {
        "$type": "color",
        "$value": "#c7cdd5"
      },
      "Neutral-300": {
        "$type": "color",
        "$value": "#adb6c1"
      },
      "Neutral-400": {
        "$type": "color",
        "$value": "#9da8b5"
      },
      "Neutral-500": {
        "$type": "color",
        "$value": "#8592a3"
      },
      "Neutral-600": {
        "$type": "color",
        "$value": "#798594"
      },
      "Neutral-700": {
        "$type": "color",
        "$value": "#5e6874"
      },
      "Neutral-800": {
        "$type": "color",
        "$value": "#49505a"
      },
      "Neutral-900": {
        "$type": "color",
        "$value": "#383d44"
      },
      "Neutral-50A": {
        "$type": "color",
        "$value": "#383d441a"
      },
      "Neutral-100A": {
        "$type": "color",
        "$value": "#383d444d"
      },
      "Neutral-200A": {
        "$type": "color",
        "$value": "#383d4480"
      },
      "Neutral-300A": {
        "$type": "color",
        "$value": "#383d44b3"
      },
      "Neutral-400A": {
        "$type": "color",
        "$value": "#383d44e6"
      }
    }
  },
  "Sematic Color Token.json/Default": {
    "color": {
      "bg": {
        "base": {
          "$type": "color",
          "$value": "{color.Neutral-0}",
          "$description": "Background for most UI surfaces, creating a neutral canvas."
        },
        "inverse": {
          "$type": "color",
          "$value": "{color.Neutral-900}"
        },
        "surfacePrimary": {
          "$type": "color",
          "$value": "{color.Neutral-50}"
        },
        "surfaceSecondary": {
          "$type": "color",
          "$value": "{color.Neutral-100}"
        },
        "overlay": {
          "$type": "color",
          "$value": "{color.Neutral-100A}"
        },
        "disabled": {
          "$type": "color",
          "$value": "{color.Neutral-200}"
        },
        "primary": {
          "light": {
            "$type": "color",
            "$value": "{color.asparagus-50}"
          },
          "idle": {
            "$type": "color",
            "$value": "{color.asparagus-500}"
          },
          "hovered": {
            "$type": "color",
            "$value": "{color.asparagus-400}"
          },
          "focused": {
            "$type": "color",
            "$value": "{color.asparagus-200}"
          }
        },
        "negative": {
          "light": {
            "$type": "color",
            "$value": "{color.red-50}"
          },
          "idle": {
            "$type": "color",
            "$value": "{color.red-500}"
          },
          "hovered": {
            "$type": "color",
            "$value": "{color.red-400}"
          },
          "focused": {
            "$type": "color",
            "$value": "{color.red-200}"
          }
        },
        "positive": {
          "light": {
            "$type": "color",
            "$value": "{color.green-50}"
          },
          "idle": {
            "$type": "color",
            "$value": "{color.green-500}"
          },
          "hovered": {
            "$type": "color",
            "$value": "{color.green-400}"
          },
          "focused": {
            "$type": "color",
            "$value": "{color.green-200}"
          }
        },
        "warning": {
          "light": {
            "$type": "color",
            "$value": "{color.orange-50}"
          },
          "idle": {
            "$type": "color",
            "$value": "{color.orange-500}"
          },
          "hovered": {
            "$type": "color",
            "$value": "{color.orange-400}"
          },
          "focused": {
            "$type": "color",
            "$value": "{color.orange-200}"
          }
        },
        "info": {
          "light": {
            "$type": "color",
            "$value": "{color.blue-50}"
          },
          "idle": {
            "$type": "color",
            "$value": "{color.blue-500}"
          },
          "hovered": {
            "$type": "color",
            "$value": "{color.blue-400}"
          },
          "focused": {
            "$type": "color",
            "$value": "{color.blue-200}"
          }
        },
        "accent": {
          "azure": {
            "$type": "color",
            "$value": "{color.dandelion-500}"
          },
          "olive": {
            "$type": "color",
            "$value": "{color.froly-500}"
          }
        }
      },
      "text": {
        "primary": {
          "$type": "color",
          "$value": "{color.Neutral-800}"
        },
        "secondary": {
          "$type": "color",
          "$value": "{color.Neutral-600}"
        },
        "bold": {
          "$type": "color",
          "$value": "{color.Neutral-900}"
        },
        "disabled": {
          "$type": "color",
          "$value": "{color.Neutral-400}"
        },
        "inverse": {
          "$type": "color",
          "$value": "{color.Neutral-0}"
        },
        "inverseSecondary": {
          "$type": "color",
          "$value": "{color.Neutral-50}"
        },
        "disabledOnDark": {
          "$type": "color",
          "$value": "{color.Neutral-200}"
        },
        "brand": {
          "$type": "color",
          "$value": "{color.asparagus-500}"
        },
        "negative": {
          "$type": "color",
          "$value": "{color.red-500}"
        },
        "positive": {
          "$type": "color",
          "$value": "{color.green-500}"
        },
        "warning": {
          "$type": "color",
          "$value": "{color.orange-500}"
        },
        "info": {
          "$type": "color",
          "$value": "{color.blue-500}"
        }
      },
      "icon": {
        "primary": {
          "$type": "color",
          "$value": "{color.Neutral-800}"
        },
        "secondary": {
          "$type": "color",
          "$value": "{color.Neutral-600}"
        },
        "bold": {
          "$type": "color",
          "$value": "{color.Neutral-900}"
        },
        "disabled": {
          "$type": "color",
          "$value": "{color.Neutral-400}"
        },
        "inverse": {
          "$type": "color",
          "$value": "{color.Neutral-0}"
        },
        "inverseSecondary": {
          "$type": "color",
          "$value": "{color.Neutral-50}"
        },
        "disabledOnDark": {
          "$type": "color",
          "$value": "{color.Neutral-200}"
        },
        "brand": {
          "$type": "color",
          "$value": "{color.asparagus-500}"
        },
        "negative": {
          "$type": "color",
          "$value": "{color.red-500}"
        },
        "positive": {
          "$type": "color",
          "$value": "{color.green-500}"
        },
        "warning": {
          "$type": "color",
          "$value": "{color.orange-500}"
        },
        "info": {
          "$type": "color",
          "$value": "{color.blue-500}"
        }
      },
      "border": {
        "primary": {
          "$type": "color",
          "$value": "{color.Neutral-800}"
        },
        "secondary": {
          "$type": "color",
          "$value": "{color.Neutral-600}"
        },
        "inverse": {
          "$type": "color",
          "$value": "{color.Neutral-0}"
        },
        "brand": {
          "light": {
            "$type": "color",
            "$value": "{color.asparagus-50}"
          },
          "default": {
            "$type": "color",
            "$value": "{color.asparagus-500}"
          },
          "bold": {
            "$type": "color",
            "$value": "{color.asparagus-700}"
          }
        },
        "negative": {
          "light": {
            "$type": "color",
            "$value": "{color.red-50}"
          },
          "default": {
            "$type": "color",
            "$value": "{color.red-500}"
          },
          "bold": {
            "$type": "color",
            "$value": "{color.red-700}"
          }
        },
        "positive": {
          "light": {
            "$type": "color",
            "$value": "{color.green-50}"
          },
          "default": {
            "$type": "color",
            "$value": "{color.green-500}"
          },
          "bold": {
            "$type": "color",
            "$value": "{color.green-700}"
          }
        },
        "warning": {
          "light": {
            "$type": "color",
            "$value": "{color.orange-50}"
          },
          "default": {
            "$type": "color",
            "$value": "{color.orange-500}"
          },
          "bold": {
            "$type": "color",
            "$value": "{color.orange-700}"
          }
        },
        "info": {
          "light": {
            "$type": "color",
            "$value": "{color.blue-50}"
          },
          "default": {
            "$type": "color",
            "$value": "{color.blue-500}"
          },
          "bold": {
            "$type": "color",
            "$value": "{color.blue-700}"
          }
        }
      }
    }
  },
  "Typography Token/Default": {
    "fontFamily": {
      "heading": {
        "$type": "text",
        "$value": "Poppin"
      },
      "body": {
        "$type": "text",
        "$value": "Poppin"
      },
      "label": {
        "$type": "text",
        "$value": "Poppin"
      },
      "caption": {
        "$type": "text",
        "$value": "Poppin"
      },
      "buttontext": {
        "$type": "text",
        "$value": "Poppin"
      }
    },
    "fontWeight": {
      "regular": {
        "$type": "text",
        "$value": "Regular"
      },
      "bold": {
        "$type": "text",
        "$value": "Bold"
      }
    },
    "fontSize": {
      "jumbo": {
        "$type": "number",
        "$value": 40
      },
      "2xl": {
        "$type": "number",
        "$value": 32
      },
      "xl": {
        "$type": "number",
        "$value": 24
      },
      "lg": {
        "$type": "number",
        "$value": 20
      },
      "md": {
        "$type": "number",
        "$value": 16
      },
      "sm": {
        "$type": "number",
        "$value": 14
      }
    },
    "lineHeight": {
      "jumbo": {
        "$type": "number",
        "$value": 56
      },
      "2xl": {
        "$type": "number",
        "$value": 48
      },
      "xl": {
        "$type": "number",
        "$value": 36
      },
      "lg": {
        "$type": "number",
        "$value": 30
      },
      "md": {
        "$type": "number",
        "$value": 24
      },
      "sm": {
        "$type": "number",
        "$value": 20
      }
    }
  },
  "Core/Default": {
    "Core": {
      "borderRadius": {
        "borderRadius-base": {
          "$type": "number",
          "$value": 4
        },
        "borderRadius-sm": {
          "$type": "number",
          "$value": 6
        },
        "borderRadius-lg": {
          "$type": "number",
          "$value": 16
        },
        "borderRadius-2xl": {
          "$type": "number",
          "$value": 32
        },
        "borderRadius-jumbo": {
          "$type": "number",
          "$value": 10000
        }
      },
      "spacing": {
        "spacing-none": {
          "$type": "number",
          "$value": 0
        },
        "spacing-base": {
          "$type": "number",
          "$value": 4
        },
        "spacing-sm": {
          "$type": "number",
          "$value": 8
        },
        "spacing-lg": {
          "$type": "number",
          "$value": 16
        },
        "spacing-xl": {
          "$type": "number",
          "$value": 24
        },
        "spacing-2xl": {
          "$type": "number",
          "$value": 32
        },
        "jumbo": {
          "$type": "number",
          "$value": 64
        }
      },
      "borderWidth": {
        "1": {
          "$type": "number",
          "$value": 1
        },
        "2": {
          "$type": "number",
          "$value": 2
        },
        "05": {
          "$type": "number",
          "$value": 0.5
        }
      }
    }
  },
  "$themes": [],
  "$metadata": {
    "tokenSetOrder": [
      "Core Color Token/Default",
      "Sematic Color Token.json/Default",
      "Typography Token/Default",
      "Core/Default"
    ]
  }
}